setup.py
salure_helpers/profit/__init__.py
salure_helpers/profit/profit_data_cleaner.py
salure_helpers/profit/profit_get.py
salure_helpers/profit/profit_get_async.py
salure_helpers/profit/profit_update.py
salure_helpers_profit.egg-info/PKG-INFO
salure_helpers_profit.egg-info/SOURCES.txt
salure_helpers_profit.egg-info/dependency_links.txt
salure_helpers_profit.egg-info/not-zip-safe
salure_helpers_profit.egg-info/requires.txt
salure_helpers_profit.egg-info/top_level.txt