Metadata-Version: 1.0
Name: salure-helpers-profit
Version: 3.0.2
Summary: Profit wrapper from Salure
Home-page: UNKNOWN
Author: D&A Salure
Author-email: support@salureconnnect.com
License: Salure License
Platform: UNKNOWN
